MANIFEST.in
README.md
setup.py
OpenHGNN/config.ini
OpenHGNN/dataset/README.md
OpenHGNN/models/README.md
OpenHGNN/output/CompGCN/README.md
OpenHGNN/output/GTN/README.md
OpenHGNN/output/HAN/README.md
OpenHGNN/output/HetGNN/README.md
OpenHGNN/output/MAGNN/README.md
OpenHGNN/output/MAGNN_AC/README.md
OpenHGNN/output/NSHE/README.md
OpenHGNN/output/RGCN/README.md
OpenHGNN/output/RSHN/README.md
OpenHGNN/output/metapath2vec/README.md
OpenHGNN/trainerflow/README.md
openhgnn/__init__.py
openhgnn/config.py
openhgnn/start.py
openhgnn/test.py
openhgnn/version.py
openhgnn/dataset/LinkPredictionDataset.py
openhgnn/dataset/NodeClassificationDataset.py
openhgnn/dataset/__init__.py
openhgnn/dataset/academic_graph.py
openhgnn/dataset/base_dataset.py
openhgnn/dataset/knowledge_graph.py
openhgnn/dataset/utils.py
openhgnn/models/CompGCN.py
openhgnn/models/EmbedLayer.py
openhgnn/models/GTN.py
openhgnn/models/GTN_sparse.py
openhgnn/models/HAN.py
openhgnn/models/HGConv.py
openhgnn/models/HGNN_AC.py
openhgnn/models/HGT.py
openhgnn/models/HGT_hetero.py
openhgnn/models/HetGNN.py
openhgnn/models/HeteroGraphConv.py
openhgnn/models/MAGNN.py
openhgnn/models/MAGNN_AC.py
openhgnn/models/Metapath2vec.py
openhgnn/models/Micro_layer.py
openhgnn/models/Multi_level.py
openhgnn/models/NEW_model.py
openhgnn/models/NSHE.py
openhgnn/models/RGCN.py
openhgnn/models/RSHN.py
openhgnn/models/__init__.py
openhgnn/models/base_model.py
openhgnn/sampler/HGT_sampler.py
openhgnn/sampler/HetGNN_sampler.py
openhgnn/sampler/RSHN_sampler.py
openhgnn/sampler/__init__.py
openhgnn/tasks/__init__.py
openhgnn/tasks/base_task.py
openhgnn/tasks/link_prediction.py
openhgnn/tasks/node_classification.py
openhgnn/trainerflow/__init__.py
openhgnn/trainerflow/base_flow.py
openhgnn/trainerflow/dist_mult.py
openhgnn/trainerflow/entity_classification.py
openhgnn/trainerflow/hetgnn_trainer.py
openhgnn/trainerflow/hgt_trainer.py
openhgnn/trainerflow/networkschema.py
openhgnn/trainerflow/node_classification.py
testopenhgnn.egg-info/PKG-INFO
testopenhgnn.egg-info/SOURCES.txt
testopenhgnn.egg-info/dependency_links.txt
testopenhgnn.egg-info/requires.txt
testopenhgnn.egg-info/top_level.txt