Metadata-Version: 2.1
Name: testopenhgnn
Version: 1.2
Summary: OpenHGNN: an open-source toolkit for Heterogeneous Graph Neural Network
Home-page: https://github.com/BUPT-GAMMA/OpenHGNN
Author: 
Author-email: 
Maintainer: 
License: UNKNOWN
Download-URL: https://github.com/BUPT-GAMMA/OpenHGNN
Platform: UNKNOWN
Classifier: Development Status :: 4 - Beta
Classifier: Programming Language :: Python :: 3.6
Requires-Python: >=3.6
